.gitignore
CHANGES.txt
CONTRIBUTORS.txt
MANIFEST.in
README.rst
bootstrap.py
buildout.cfg
setup.py
src/collective/__init__.py
src/collective.ploneslimbar.egg-info/PKG-INFO
src/collective.ploneslimbar.egg-info/SOURCES.txt
src/collective.ploneslimbar.egg-info/dependency_links.txt
src/collective.ploneslimbar.egg-info/entry_points.txt
src/collective.ploneslimbar.egg-info/namespace_packages.txt
src/collective.ploneslimbar.egg-info/not-zip-safe
src/collective.ploneslimbar.egg-info/requires.txt
src/collective.ploneslimbar.egg-info/top_level.txt
src/collective/ploneslimbar/__init__.py
src/collective/ploneslimbar/configure.zcml
src/collective/ploneslimbar/ico_plone_mini.png
src/collective/ploneslimbar/interfaces.py
src/collective/ploneslimbar/slimbar.css
src/collective/ploneslimbar/slimbar.pt
src/collective/ploneslimbar/viewlet.py
src/collective/ploneslimbar/profiles/default/browserlayer.xml
src/collective/ploneslimbar/profiles/default/cssregistry.xml
src/collective/ploneslimbar/profiles/default/jsregistry.xml
src/collective/ploneslimbar/profiles/default/metadata.xml
src/collective/ploneslimbar/profiles/default/viewlets.xml