Metadata-Version: 1.0
Name: collective.ploneslimbar
Version: 1.0
Summary: slimbar for listing local communities sites
Home-page: http://github.com/collective/collective.ploneslimbar
Author: Maurizio Delmonte, Abstract
Author-email: maurizio.delmonte@abstract.it
License: gpl
Keywords: plone
Platform: UNKNOWN
Classifier: Programming Language :: Python
Classifier: Framework :: Plone
Classifier: Topic :: Software Development :: Libraries :: Python Modules
